flysight2csv/__init__.py
flysight2csv/__main__.py
flysight2csv/cli.py
flysight2csv/const.py
flysight2csv/parsed.py
flysight2csv/parser.py
flysight2csv/program.py
flysight2csv/program_params.py
flysight2csv/py.typed
flysight2csv/reformatter.py
flysight2csv/selection.py
flysight2csv/version.py
flysight2csv-0.2.3.dist-info/LICENSE
flysight2csv-0.2.3.dist-info/METADATA
flysight2csv-0.2.3.dist-info/WHEEL
flysight2csv-0.2.3.dist-info/entry_points.txt
flysight2csv-0.2.3.dist-info/RECORD
