Metadata-Version: 2.1
Name: flysight2csv
Version: 0.2.3
Summary: Utilities for finding and reformatting FlySight 2 CSV files (SENSOR.CSV and TRACK.CSV).
Home-page: https://github.com/yoleg/flysight2csv
License: MIT
Author: Oleg Pryadko
Author-email: oleg@olegpryadko.com
Requires-Python: >=3.10,<4.0
Classifier: Development Status :: 2 - Pre-Alpha
Classifier: Environment :: Console
Classifier: Intended Audience :: Developers
Classifier: Intended Audience :: End Users/Desktop
Classifier: License :: OSI Approved :: MIT License
Classifier: Natural Language :: English
Classifier: Operating System :: OS Independent
Classifier: Programming Language :: Python :: 3
Classifier: Programming Language :: Python :: 3.10
Classifier: Programming Language :: Python :: 3.11
Classifier: Programming Language :: Python :: 3.12
Classifier: Topic :: Scientific/Engineering
Classifier: Topic :: Utilities
Requires-Dist: pydantic (>=2.5.3,<3.0.0)
Requires-Dist: rich (>=10)
Requires-Dist: rich-argparse (>=1.4.0,<2.0.0)
Requires-Dist: simplejson (>=3.19.2,<4.0.0)
Requires-Dist: types-simplejson (>=3.19.0.2,<4.0.0.0)
Project-URL: Bug Tracker, https://github.com/yoleg/flysight2csv/issues
Project-URL: Changelog, https://github.com/yoleg/flysight2csv/blob/main/CHANGELOG.md
Project-URL: Documentation, https://flysight2csv.readthedocs.io
Project-URL: Repository, https://github.com/yoleg/flysight2csv
